Metadata-Version: 1.1
Name: itamae
Version: 0.1.1
Summary: Python 802.11 MPDU and Radiotap parsing
Home-page: http://wraith-wireless.github.io/itamae/
Author: Dale Patterson
Author-email: wraith.wireless@yandex.com
License: GPL v3.0
Download-URL: https://github.com/wraith-wireless/itamae/archive/0.1.1.tar.gz
Keywords: 802.11 wireless WLAN WiFi parser MPDU,radiotap
Platform: UNKNOWN
Classifier: Development Status :: 5 - Production/Stable
Classifier: License :: OSI Approved :: GNU General Public License v3 (GPLv3)
Classifier: Intended Audience :: Developers
Classifier: Topic :: Software Development
Classifier: Topic :: Software Development :: Libraries
Classifier: Topic :: System :: Networking
Classifier: Topic :: Utilities
Classifier: Operating System :: POSIX :: Linux
Classifier: Operating System :: MacOS
Classifier: Operating System :: Microsoft :: Windows
Classifier: Programming Language :: Python
Classifier: Programming Language :: Python :: 2.7
